[{
    "name": "Мотошолом Shark D-Skwal 2 Blank",
    "price": 8420,
    "url": "./img/motoshlem-shark-ridill-blank-black-l-300x300.webp",
    "squ": 144887,
    "color": "BLACK MATT"
},

{
    "name": "Мотошолом SCORPION VX-15 EVO AIR GRID",
    "price": 4230,
    "url": "./img/motoshlem-scorpion-vx-15-evo-air-grid-pearl-white-red-blue-m5-300x300.webp",
    "squ": 53960,
    "color": "WHITE-RED-BLUE"
}, 

{
    "name": "Мотошолом X-LITE X-903 UC MODERN",
    "price": 17780,
    "url": "./img/motoshlem-x-lite-x-903-uc-modern-class-n-com-double-d-ring-carbon-300x300.webp",
    "squ": 138729,
    "color": "CARBON"
}, 

{
    "name": "Мотошолом KYT NF-J RADAR",
    "price": 5490,
    "url": "./img/akva1-300x300.webp",
    "squ": 161456,
    "color": "AQUA BLUE"
}, 

{
    "name": "Мотошолом CABERG XTRACE",
    "price": 6220,
    "url": "./img/motoshlem-caberg-xtrace-matt-black-nl-l2-300x300.webp",
    "squ": 108776,
    "color": "MATT BLACK"
},

{
    "name": "Мотошолом AGV K-1 ",
    "price": 6540,
    "url": "./img/agv-k1-300x300.webp",
    "squ": 138624,
    "color": "WHITE"
},

{
    "name": "Мотошолом AIROH RIOT LIFESTYLE",
    "price": 7960,
    "url": "./img/motoshlem-airoh-riot-lifestyle-matt-black-l1-300x300.webp",
    "squ": 73566,
    "color": "MATT BLACK"
},

{
    "name": "Мотошолом AGV K-3 SV",
    "price": 8840,
    "url": "./img/agv-shlem-agv-k3-sv-birdy-50-skidka-na-vizor-300x300.webp",
    "squ": 147594,
    "color": "BIRDY"
},

{
    "name": "Мотошолом HJC RPHA MAX",
    "price": 9670,
    "url": "./img/shlem-hjc-rpha-max-black-l-300x300.webp",
    "squ": 26359,
    "color": "BLACK"
},

{
    "name": "Мотошолом HJC RPHA 10 PLUS FURIA MC1",
    "price": 10790,
    "url": "./img/motoshlem-hjc-rpha-10-plus-furia-mc7-black-orange-l1-300x300.webp",
    "squ": 44539,
    "color": "BLACK-RED"
}

]